{
  "nio/AlphaDisplay": {
    "language": "Python",
    "url": "git://github.com/nio-blocks/rainbow_hat.git",
    "version": "0.1.0"
  },
  "nio/AndroidThingsButton": {
    "language": "Python",
    "url": "git://github.com/nio-blocks/rainbow_hat.git",
    "version": "0.1.0"
  },
  "nio/AndroidThingsRGB": {
    "language": "Python",
    "url": "git://github.com/nio-blocks/rainbow_hat.git",
    "version": "0.1.0"
  },
  "nio/Buzzer": {
    "language": "Python",
    "url": "git://github.com/nio-blocks/rainbow_hat.git",
    "version": "0.1.0"
  },
  "nio/FloatDisplay": {
    "language": "Python",
    "url": "git://github.com/nio-blocks/rainbow_hat.git",
    "version": "0.1.0"
  },
  "nio/LedStrip": {
    "language": "Python",
    "url": "git://github.com/nio-blocks/rainbow_hat.git",
    "version": "0.1.0"
  },
  "nio/TemperatureSensor": {
    "language": "Python",
    "url": "git://github.com/nio-blocks/rainbow_hat.git",
    "version": "0.1.0"
  }
}